CHANGELOG.md
LICENSE
MANIFEST.in
README.md
Tutorial.md
setup.py
PyCSCL.egg-info/PKG-INFO
PyCSCL.egg-info/SOURCES.txt
PyCSCL.egg-info/dependency_links.txt
PyCSCL.egg-info/top_level.txt
cscl/__init__.py
cscl/basic_gate_encoders.py
cscl/bitvector_gate_encoders.py
cscl/cardinality_constraint_encoders.py
cscl/dimacs_printer.py
cscl/interfaces.py
cscl/ipasir.py
cscl_examples/__init__.py
cscl_examples/factorization.py
cscl_examples/sudoku.py
cscl_examples/smt_qfbv_solver/__init__.py
cscl_examples/smt_qfbv_solver/ast.py
cscl_examples/smt_qfbv_solver/ast_transformers.py
cscl_examples/smt_qfbv_solver/sexp_parser.py
cscl_examples/smt_qfbv_solver/smtlib2_parser.py
cscl_examples/smt_qfbv_solver/sorts.py
cscl_examples/smt_qfbv_solver/syntactic_scope.py
cscl_examples/smt_qfbv_solver/theories.py
cscl_tests/__init__.py
cscl_tests/cscl/__init__.py
cscl_tests/cscl/unit/__init__.py
cscl_tests/cscl/unit/test_basic_gate_encoders.py
cscl_tests/cscl/unit/test_bitvector_gate_encoders.py
cscl_tests/cscl/unit/test_cardinality_constraint_encoders.py
cscl_tests/cscl/unit/test_dimacs_printer.py
cscl_tests/examples/__init__.py
cscl_tests/examples/test_factorization.py
cscl_tests/examples/test_sudoku.py
cscl_tests/examples/smt_qfbv_solver/__init__.py
cscl_tests/examples/smt_qfbv_solver/integration/__init__.py
cscl_tests/examples/smt_qfbv_solver/integration/test_str_to_inlined_ast.py
cscl_tests/examples/smt_qfbv_solver/integration/test_str_to_smtlib2_parser.py
cscl_tests/examples/smt_qfbv_solver/unit/__init__.py
cscl_tests/examples/smt_qfbv_solver/unit/test_ast_transformers.py
cscl_tests/examples/smt_qfbv_solver/unit/test_sexp_parser.py
cscl_tests/examples/smt_qfbv_solver/unit/test_smtlib2_parser.py
cscl_tests/examples/smt_qfbv_solver/unit/test_sorts.py
cscl_tests/examples/smt_qfbv_solver/unit/test_syntactic_scope.py
cscl_tests/examples/smt_qfbv_solver/unit/test_theories.py
cscl_tests/testutils/__init__.py
cscl_tests/testutils/logging_clause_consumer_decorator.py
cscl_tests/testutils/test_trivial_sat_solver.py
cscl_tests/testutils/trivial_sat_solver.py
pycscl.egg-info/PKG-INFO
pycscl.egg-info/SOURCES.txt
pycscl.egg-info/dependency_links.txt
pycscl.egg-info/top_level.txt