Metadata-Version: 2.1
Name: pycscl
Version: 0.2.0
Summary: UNKNOWN
Home-page: https://github.com/fkutzner/PyCSCL
Author: Felix Kutzner
Author-email: felixkutzner@gmail.com
License: MIT
Platform: UNKNOWN
